psyneulink_sphinx_theme.py
psyneulink_sphinx_theme/__init__.py
psyneulink_sphinx_theme/breadcrumbs.html
psyneulink_sphinx_theme/cookie_banner.html
psyneulink_sphinx_theme/fonts.html
psyneulink_sphinx_theme/footer.html
psyneulink_sphinx_theme/layout.html
psyneulink_sphinx_theme/search.html
psyneulink_sphinx_theme/searchbox.html
psyneulink_sphinx_theme/theme.conf
psyneulink_sphinx_theme/theme_variables.jinja
psyneulink_sphinx_theme/versions.html
psyneulink_sphinx_theme/static/css/theme.css
psyneulink_sphinx_theme/static/fonts/FreightSans/freight-sans-bold-italic.woff
psyneulink_sphinx_theme/static/fonts/FreightSans/freight-sans-bold-italic.woff2
psyneulink_sphinx_theme/static/fonts/FreightSans/freight-sans-bold.woff
psyneulink_sphinx_theme/static/fonts/FreightSans/freight-sans-bold.woff2
psyneulink_sphinx_theme/static/fonts/FreightSans/freight-sans-book-italic.woff
psyneulink_sphinx_theme/static/fonts/FreightSans/freight-sans-book-italic.woff2
psyneulink_sphinx_theme/static/fonts/FreightSans/freight-sans-book.woff
psyneulink_sphinx_theme/static/fonts/FreightSans/freight-sans-book.woff2
psyneulink_sphinx_theme/static/fonts/FreightSans/freight-sans-light-italic.woff
psyneulink_sphinx_theme/static/fonts/FreightSans/freight-sans-light-italic.woff2
psyneulink_sphinx_theme/static/fonts/FreightSans/freight-sans-light.woff
psyneulink_sphinx_theme/static/fonts/FreightSans/freight-sans-light.woff2
psyneulink_sphinx_theme/static/fonts/FreightSans/freight-sans-medium-italic.woff
psyneulink_sphinx_theme/static/fonts/FreightSans/freight-sans-medium-italic.woff2
psyneulink_sphinx_theme/static/fonts/FreightSans/freight-sans-medium.woff
psyneulink_sphinx_theme/static/fonts/FreightSans/freight-sans-medium.woff2
psyneulink_sphinx_theme/static/fonts/IBMPlexMono/IBMPlexMono-Light.woff
psyneulink_sphinx_theme/static/fonts/IBMPlexMono/IBMPlexMono-Light.woff2
psyneulink_sphinx_theme/static/fonts/IBMPlexMono/IBMPlexMono-Medium.woff
psyneulink_sphinx_theme-1.2.7.dist-info/METADATA
psyneulink_sphinx_theme-1.2.7.dist-info/WHEEL
psyneulink_sphinx_theme-1.2.7.dist-info/entry_points.txt
psyneulink_sphinx_theme-1.2.7.dist-info/top_level.txt
psyneulink_sphinx_theme-1.2.7.dist-info/RECORD
