Metadata-Version: 2.4
Name: psyneulink_sphinx_theme
Version: 1.2.7
Summary: PsyNeuLink Sphinx Theme
Home-page: https://github.com/kmantel/psyneulink-sphinx-theme
Author: Dillon Smith
Author-email: dillon.th.smith@gmail.com
License: MIT License
Classifier: Development Status :: 5 - Production/Stable
Classifier: Environment :: Web Environment
Classifier: Intended Audience :: Developers
Classifier: Intended Audience :: System Administrators
Classifier: License :: OSI Approved :: MIT License
Classifier: Operating System :: OS Independent
Classifier: Programming Language :: Python
Classifier: Topic :: Internet
Classifier: Topic :: Software Development :: Documentation
Requires-Dist: sphinx
Requires-Dist: sphinxcontrib-jquery
Dynamic: author
Dynamic: author-email
Dynamic: classifier
Dynamic: home-page
Dynamic: license
Dynamic: requires-dist
Dynamic: summary
